spintop/VERSION
spintop/__init__.py
spintop/__main__.py
spintop/cli.py
spintop/compat.py
spintop/env.py
spintop/errors.py
spintop/logs.py
spintop/spintop.py
spintop/storage.py
spintop/analytics/__init__.py
spintop/analytics/base.py
spintop/analytics/bigquery.py
spintop/analytics/postgresql.py
spintop/analytics/singer.py
spintop/api_client/__init__.py
spintop/api_client/analytics.py
spintop/api_client/auth_bootstrap.py
spintop/api_client/base.py
spintop/api_client/persistence_facade.py
spintop/api_client/schemas.py
spintop/auth/__init__.py
spintop/auth/base.py
spintop/auth/schemas.py
spintop/auth/store.py
spintop/examples/__init__.py
spintop/examples/login.py
spintop/generators/__init__.py
spintop/generators/base.py
spintop/generators/files_gen.py
spintop/generators/random_gen.py
spintop/messages/__init__.py
spintop/messages/base.py
spintop/messages/models.py
spintop/models/__init__.py
spintop/models/base.py
spintop/models/meta.py
spintop/models/persistence.py
spintop/models/queries.py
spintop/models/serialization.py
spintop/models/view.py
spintop/models/view_helpers.py
spintop/models/test_records/__init__.py
spintop/models/test_records/_base.py
spintop/models/test_records/_collection.py
spintop/models/test_records/_tree_struct.py
spintop/persistence/__init__.py
spintop/persistence/base.py
spintop/persistence/mongo/__init__.py
spintop/persistence/mongo/facade.py
spintop/persistence/mongo/mappers.py
spintop/persistence/mongo/operations.py
spintop/persistence/mongo/queryset.py
spintop/persistence/mongo/serialization.py
spintop/persistence/postgresql/__init__.py
spintop/persistence/postgresql/facade.py
spintop/persistence/postgresql/models.py
spintop/persistence/postgresql/operations.py
spintop/persistence/postgresql/queryset.py
spintop/services/__init__.py
spintop/services/auth0.py
spintop/services/target_bigquery.py
spintop/testing/__init__.py
spintop/testing/integration_config.py
spintop/testing/plugin.py
spintop/transforms/__init__.py
spintop/transforms/base.py
spintop-0.8.3.post0.dist-info/LICENSE
spintop-0.8.3.post0.dist-info/METADATA
spintop-0.8.3.post0.dist-info/WHEEL
spintop-0.8.3.post0.dist-info/top_level.txt
spintop-0.8.3.post0.dist-info/RECORD
