Metadata-Version: 2.1
Name: spintop
Version: 0.8.3.post0
Summary: The python client to spintop.io
Home-page: UNKNOWN
Author: William Laroche
Author-email: william.laroche@tackv.ca
Maintainer: William Laroche
Maintainer-email: william.laroche@tackv.ca
License: UNKNOWN
Platform: UNKNOWN
Requires-Dist: anytree
Requires-Dist: appdirs
Requires-Dist: click
Requires-Dist: cryptography
Requires-Dist: dataclasses (>=0.6)
Requires-Dist: gitpython
Requires-Dist: jinja2
Requires-Dist: marshmallow (>=3.5)
Requires-Dist: marshmallow-dataclass
Requires-Dist: marshmallow-union
Requires-Dist: pkginfo
Requires-Dist: PyJWT
Requires-Dist: psutil
Requires-Dist: pytz
Requires-Dist: pyyaml
Requires-Dist: python-dateutil
Requires-Dist: requests
Requires-Dist: tabulate
Requires-Dist: tblib
Requires-Dist: incremental-module-loader
Requires-Dist: simplejson
Requires-Dist: simple-memory-cache
Requires-Dist: xmltodict
Provides-Extra: bigquery
Requires-Dist: jsonschema (>=2.6.0) ; extra == 'bigquery'
Requires-Dist: singer-python (>=1.5.0) ; extra == 'bigquery'
Requires-Dist: google-api-python-client (>=1.6.2) ; extra == 'bigquery'
Requires-Dist: google-cloud (>=0.34.0) ; extra == 'bigquery'
Requires-Dist: google-cloud-bigquery (>=1.9.0) ; extra == 'bigquery'
Requires-Dist: oauth2client ; extra == 'bigquery'
Provides-Extra: postgres
Requires-Dist: sqlalchemy ; extra == 'postgres'
Requires-Dist: psycopg2 ; extra == 'postgres'
